banditpam.cpython-312-i386-linux-musl.so
algorithms/banditpam.cpp
algorithms/banditpam_orig.cpp
algorithms/fastpam1.cpp
algorithms/kmedoids_algorithm.cpp
algorithms/pam.cpp
banditpam-6.0.1.data/data/docs/long_desc.rst
banditpam-6.0.1.data/headers/banditpam.hpp
banditpam-6.0.1.data/headers/fastpam1.hpp
banditpam-6.0.1.data/headers/kmedoids_algorithm.hpp
banditpam-6.0.1.data/headers/kmedoids_pywrapper.hpp
banditpam-6.0.1.data/headers/pam.hpp
banditpam.libs/libgcc_s-887de51c.so.1
banditpam.libs/libgomp-24921df4.so.1.0.0
banditpam.libs/libstdc++-d6415257.so.6.0.33
python_bindings/build_medoids_python.cpp
python_bindings/cache_python.cpp
python_bindings/fit_python.cpp
python_bindings/kmedoids_pywrapper.cpp
python_bindings/labels_python.cpp
python_bindings/loss_python.cpp
python_bindings/medoids_python.cpp
python_bindings/steps_python.cpp
python_bindings/swap_times_python.cpp
banditpam-6.0.1.dist-info/METADATA
banditpam-6.0.1.dist-info/WHEEL
banditpam-6.0.1.dist-info/top_level.txt
banditpam-6.0.1.dist-info/RECORD
banditpam-6.0.1.dist-info/licenses/LICENSE
