Metadata-Version: 2.4
Name: banditpam
Version: 6.0.1
Summary: BanditPAM: A state-of-the-art, high-performance k-medoids algorithm.
Home-page: https://github.com/motiwari/BanditPAM
Author: Mo Tiwari
Author-email: Mo Tiwari <mohittiwarinyc@gmail.com>, Balasubramanian Narasimhan <naras@stanford.edu>
Maintainer: Mo Tiwari
Maintainer-email: Mo Tiwari <mohittiwarinyc@gmail.com>, Balasubramanian Narasimhan <naras@stanford.edu>
License: MIT
Requires-Python: >=3.10
License-File: LICENSE
Dynamic: author
Dynamic: home-page
Dynamic: license-file
Dynamic: maintainer
